{
    "code": 200,
    "data": {
        "confusion_matrix": [
            [
                4106,
                456,
                0,
                0
            ],
            [
                1201,
                2055,
                0,
                0
            ],
            [
                1540,
                145,
                0,
                0
            ],
            [
                265,
                1,
                0,
                0
            ]
        ],
        "labels": [
            "Married",
            "Never married",
            "Divorced or Separated",
            "Widowed"
        ]
    },
    "msg": "OK",
    "userId": "f6a411d5-988d-4c21-9700-0418482b6fac"
}